CHANGES.rst
CONTRIBUTORS.rst
README.rst
bootstrap.py
buildout.cfg
i18n.sh
setup.py
docs/LICENSE.GPL
docs/LICENSE.txt
src/raptus/__init__.py
src/raptus.article.addthis.egg-info/PKG-INFO
src/raptus.article.addthis.egg-info/SOURCES.txt
src/raptus.article.addthis.egg-info/dependency_links.txt
src/raptus.article.addthis.egg-info/entry_points.txt
src/raptus.article.addthis.egg-info/namespace_packages.txt
src/raptus.article.addthis.egg-info/not-zip-safe
src/raptus.article.addthis.egg-info/requires.txt
src/raptus.article.addthis.egg-info/top_level.txt
src/raptus/article/__init__.py
src/raptus/article/addthis/__init__.py
src/raptus/article/addthis/addthis.gif
src/raptus/article/addthis/addthis.pt
src/raptus/article/addthis/addthis.py
src/raptus/article/addthis/configure.zcml
src/raptus/article/addthis/interfaces.py
src/raptus/article/addthis/style.css
src/raptus/article/addthis/testing.py
src/raptus/article/addthis/testing.zcml
src/raptus/article/addthis/locales/manual.pot
src/raptus/article/addthis/locales/raptus.article.pot
src/raptus/article/addthis/locales/de/LC_MESSAGES/raptus.article.po
src/raptus/article/addthis/profiles/default/cssregistry.xml
src/raptus/article/addthis/profiles/default/metadata.xml
src/raptus/article/addthis/profiles/default/propertiestool.xml
src/raptus/article/addthis/profiles/default/viewlets.xml
src/raptus/article/addthis/profiles/testing/metadata.xml
src/raptus/article/addthis/tests/__init__.py
src/raptus/article/addthis/tests/test_setup.py