Metadata-Version: 1.1
Name: raptus.article.addthis
Version: 1.0
Summary: raptus.article component that adds addthis social buttons below the text
Home-page: https://github.com/frisi/raptus.article.addthis
Author: Harald Friessnegger
Author-email: harald (at) webmeisterei dot com
License: gpl
Keywords: plone,addthis,social,bookmarks
Platform: UNKNOWN
Classifier: Environment :: Web Environment
Classifier: Framework :: Plone
Classifier: Operating System :: OS Independent
Classifier: Programming Language :: Python
Classifier: Programming Language :: Python :: 2.6
Classifier: Topic :: Software Development :: Libraries :: Python Modules
